cotwo/__init__.py
cotwo/molecule.py
cotwo/io/__init__.py
cotwo/io/xyz.py
cotwo/rendering/__init__.py
cotwo/rendering/atom.py
cotwo/rendering/bond.py
cotwo/rendering/isosurface.py
cotwo/rendering/meshes.py
cotwo/resources/__init__.py
cotwo/resources/bond_types.py
cotwo/resources/periodic_table.json
cotwo-1.2.0.dist-info/METADATA
cotwo-1.2.0.dist-info/WHEEL
cotwo-1.2.0.dist-info/RECORD
