Metadata-Version: 2.4
Name: cotwo
Version: 1.2.0
Summary: Simple visualizer for molecules and isosurfaces with Plotly
Project-URL: repository, https://codeberg.org/crabby/cotwo
Author-email: crabby <frederik.scherz@tu-darmstadt.de>
Requires-Python: >=3.11
Requires-Dist: numpy>=2.2.3
Requires-Dist: plotly>=6.0.0
Requires-Dist: polars>=1.24.0
Requires-Dist: rdkit>=2024.9.5
Requires-Dist: scikit-image>=0.25.2
Requires-Dist: scipy>=1.15.2
